LICENSE
README.md
setup.py
haberpy/__init__.py
haberpy.egg-info/PKG-INFO
haberpy.egg-info/SOURCES.txt
haberpy.egg-info/dependency_links.txt
haberpy.egg-info/top_level.txt
haberpy/sondakika/__init__.py
haberpy/sondakika/economy.py
haberpy/sondakika/magazine.py
haberpy/sondakika/policy.py
haberpy/sondakika/sport.py