Metadata-Version: 2.1
Name: haberpy
Version: 0.0.3
Summary: Haber sitelerinden bildirimleri kolay sekilde alabilmeniz icin tasarlanmis bir Python API
Home-page: https://github.com/Meinos10/haberpy
Author: Emre
Author-email: rewoxirewo@gmail.com
License: MIT
Keywords: haberpy,haberpython,haber,haber-python,haber-py,sondakika,son-dakika
Requires: requests
Requires: beautifulsoup4
License-File: LICENSE
